{
	"name": "hud_skill",
	"plugin-id": "Sprite",
	"sid": 578544087106106,
	"isGlobal": false,
	"instanceVariables": [
		{
			"name": "playerIndex",
			"type": "number",
			"desc": "",
			"show": true,
			"sid": 804285814742703
		},
		{
			"name": "owner",
			"type": "number",
			"desc": "",
			"show": true,
			"sid": 386750918045948
		}
	],
	"behaviorTypes": [],
	"effectTypes": [],
	"animations": {
		"items": [
			{
				"frames": [
					{
						"width": 25,
						"height": 25,
						"originX": 0.5,
						"originY": 0.5,
						"originalSource": "",
						"exportFormat": "lossless",
						"exportQuality": 0.8,
						"imageSpriteId": 9748546,
						"useCollisionPoly": true,
						"imagePoints": [
							{
								"name": "spawn_mask",
								"x": 0.5,
								"y": 1
							}
						],
						"duration": 1
					}
				],
				"sid": 950244924340476,
				"name": "fundinaso",
				"isLooping": false,
				"isPingPong": false,
				"repeatCount": 1,
				"repeatTo": 0,
				"speed": 5
			},
			{
				"frames": [
					{
						"width": 25,
						"height": 25,
						"originX": 0.5,
						"originY": 0.5,
						"originalSource": "",
						"exportFormat": "lossless",
						"exportQuality": 0.8,
						"imageSpriteId": 8719437,
						"useCollisionPoly": true,
						"duration": 1
					}
				],
				"sid": 969592062251391,
				"name": "random_tp_all",
				"isLooping": false,
				"isPingPong": false,
				"repeatCount": 1,
				"repeatTo": 0,
				"speed": 5
			},
			{
				"frames": [
					{
						"width": 25,
						"height": 25,
						"originX": 0.5,
						"originY": 0.5,
						"originalSource": "",
						"exportFormat": "lossless",
						"exportQuality": 0.8,
						"imageSpriteId": 7107612,
						"useCollisionPoly": true,
						"duration": 1
					}
				],
				"sid": 845031233701237,
				"name": "ice_wall",
				"isLooping": false,
				"isPingPong": false,
				"repeatCount": 1,
				"repeatTo": 0,
				"speed": 5
			},
			{
				"frames": [
					{
						"width": 25,
						"height": 25,
						"originX": 0.5,
						"originY": 0.5,
						"originalSource": "",
						"exportFormat": "lossless",
						"exportQuality": 0.8,
						"imageSpriteId": 697045,
						"useCollisionPoly": true,
						"duration": 1
					}
				],
				"sid": 913144125189898,
				"name": "area_root",
				"isLooping": false,
				"isPingPong": false,
				"repeatCount": 1,
				"repeatTo": 0,
				"speed": 5
			},
			{
				"frames": [
					{
						"width": 25,
						"height": 25,
						"originX": 0.5,
						"originY": 0.5,
						"originalSource": "",
						"exportFormat": "lossless",
						"exportQuality": 0.8,
						"imageSpriteId": 4245855,
						"useCollisionPoly": true,
						"duration": 1
					}
				],
				"sid": 930868328873823,
				"name": "metronome",
				"isLooping": false,
				"isPingPong": false,
				"repeatCount": 1,
				"repeatTo": 0,
				"speed": 5
			},
			{
				"frames": [
					{
						"width": 25,
						"height": 25,
						"originX": 0.5,
						"originY": 0.5,
						"originalSource": "",
						"exportFormat": "lossless",
						"exportQuality": 0.8,
						"imageSpriteId": 7582255,
						"useCollisionPoly": true,
						"duration": 1
					}
				],
				"sid": 877622863311281,
				"name": "magic_marionette",
				"isLooping": false,
				"isPingPong": false,
				"repeatCount": 1,
				"repeatTo": 0,
				"speed": 5
			},
			{
				"frames": [
					{
						"width": 25,
						"height": 25,
						"originX": 0.5,
						"originY": 0.5,
						"originalSource": "",
						"exportFormat": "lossless",
						"exportQuality": 0.8,
						"imageSpriteId": 3078003,
						"useCollisionPoly": true,
						"duration": 1
					}
				],
				"sid": 475574279939568,
				"name": "stick_hook",
				"isLooping": false,
				"isPingPong": false,
				"repeatCount": 1,
				"repeatTo": 0,
				"speed": 5
			},
			{
				"frames": [
					{
						"width": 25,
						"height": 25,
						"originX": 0.5,
						"originY": 0.5,
						"originalSource": "",
						"exportFormat": "lossless",
						"exportQuality": 0.8,
						"imageSpriteId": 5837137,
						"useCollisionPoly": true,
						"duration": 1
					}
				],
				"sid": 326005760177236,
				"name": "cry_stun",
				"isLooping": false,
				"isPingPong": false,
				"repeatCount": 1,
				"repeatTo": 0,
				"speed": 5
			}
		],
		"subfolders": []
	}
}